certbot_dns_porkbun/__init__.py
certbot_dns_porkbun/cert/__init__.py
certbot_dns_porkbun/cert/client.py
tests/__init__.py
tests/cert_client.py
certbot_dns_porkbun-0.11.0.dist-info/METADATA
certbot_dns_porkbun-0.11.0.dist-info/WHEEL
certbot_dns_porkbun-0.11.0.dist-info/entry_points.txt
certbot_dns_porkbun-0.11.0.dist-info/top_level.txt
certbot_dns_porkbun-0.11.0.dist-info/RECORD
