Metadata-Version: 2.4
Name: certbot_dns_porkbun
Version: 0.11.0
Summary: Plugin for certbot to obtain certificates using a DNS TXT record for Porkbun domains
Home-page: https://github.com/infinityofspace/certbot_dns_porkbun
Author: infinityofspace
License: MIT
Classifier: Development Status :: 4 - Beta
Classifier: Programming Language :: Python :: 3
Classifier: Programming Language :: Python :: 3.10
Classifier: Programming Language :: Python :: 3.11
Classifier: Programming Language :: Python :: 3.12
Classifier: Programming Language :: Python :: 3.13
Classifier: Programming Language :: Python :: 3.14
Classifier: License :: OSI Approved :: MIT License
Classifier: Topic :: Security
Classifier: Topic :: Internet :: WWW/HTTP
Classifier: Topic :: Utilities
Classifier: Topic :: System :: Systems Administration
Requires-Python: >=3.10
Requires-Dist: setuptools>=41.6.0
Requires-Dist: certbot<6.0,>=1.18.0
Requires-Dist: pkb_client<3.0,>=2.0
Requires-Dist: dnspython<3.0,>=2.0.0
Requires-Dist: tldextract<6.0,>=5.1.2
Dynamic: author
Dynamic: classifier
Dynamic: description
Dynamic: description-content-type
Dynamic: home-page
Dynamic: license
Dynamic: requires-dist
Dynamic: requires-python
Dynamic: summary
